Workbook
Name DatosExternos_1: search_ISBI!$A$1:$B$686

Sheet search_ISBI
A1: Title | B1: Year | C1: DOI | D1: Screening 1 | E1: Review full | F1: Reason | G1: 1 | H1: 2 | I1: 3 | J1: 4 | K1: 5 | L1: 6 | M1: 7 | N1: 8 | O1: 9 | P1: 10 | Q1: 11 | R1: 12 | S1: 13 | T1: 14
A2: Legopet: Hierarchical Feature Guided Conditional Diffusion for Pet Image Reconstruction | B2: 2025 | C2: 10.1109/ISBI60581.2025.10980656 | D2: No
A3: On Frequency Domain Adversarial Vulnerabilities of Volumetric Medical Image Segmentation | B3: 2025 | C3: 10.1109/ISBI60581.2025.10981075 | D3: No
A4: Integrations: Informed Subset Selection Based Generation for Medical Imaging in Resource Constrained Setting | B4: 2025 | C4: 10.1109/ISBI60581.2025.10980935 | D4: No
A5: Targeting Prostate Biopsy: A Straightforward CNN Solution for 3D MR-Trus Image Registration | B5: 2025 | C5: 10.1109/ISBI60581.2025.10981223 | D5: No
A6: Conditional Convolution of Clinical Data Embeddings for Multimodal Prostate Cancer Classification | B6: 2025 | C6: 10.1109/ISBI60581.2025.10981307 | D6: Yes | E6: Yes | G6: Yes | H6: Partially | I6: Yes | J6: No | K6: Yes | L6: Partially | M6: Yes | N6: No | O6: Partially | P6: Partially | Q6: Partially | R6: Partially | S6: No | T6: Yes
A7: Predicting Response to Neoadjuvant Chemotherapy using Multi-Modal MRI Radiomics and Machine Learning Approaches | B7: 2025 | C7: 10.1109/ISBI60581.2025.10980916 | D7: Yes | E7: Yes | G7: Yes | H7: Partially | I7: Yes | J7: No | K7: Yes | L7: Partially | M7: Yes | N7: No | O7: Partially | P7: Partially | Q7: Partially | R7: Partially | S7: No | T7: No
A8: Towards Classifying Histopathological Microscope Images as Time Series Data | B8: 2025 | C8: 10.1109/ISBI60581.2025.10981309 | D8: Yes | E8: Yes | G8: Yes | H8: Partially | I8: Yes | J8: No | K8: Yes | L8: Partially | M8: Yes | N8: No | O8: Partially | P8: Partially | Q8: Partially | R8: Partially | S8: No | T8: No
A9: Machine Learning-Based Polysomnography Data Analysis for ADHD Diagnosis: A Focus on Sleep Stage-Based Biomarkers | B9: 2025 | C9: 10.1109/ISBI60581.2025.10981031 | D9: Yes | E9: Yes | G9: Yes | H9: Yes | I9: Yes | J9: No | K9: Yes | L9: Partially | M9: Yes | N9: No | O9: Partially | P9: Partially | Q9: Partially | R9: Partially | S9: No | T9: Yes
A10: Attention-Based Multiple Instance Learning for Achilles Tendinopathy Detection in Ultrasound Imaging | B10: 2025 | C10: 10.1109/ISBI60581.2025.10981252 | D10: Yes | E10: Yes | G10: Yes | H10: Partially | I10: Yes | J10: No | K10: Yes | L10: Yes | M10: Yes | N10: No | O10: Partially | P10: Partially | Q10: Partially | R10: Partially | S10: Partially | T10: No
A11: Ensemble of Foundation Models for Pap Smear Cell Analysis | B11: 2025 | C11: 10.1109/ISBI60581.2025.10981009 | D11: Yes | E11: Yes | G11: Yes | H11: No | I11: Yes | J11: No | K11: Yes | L11: Partially | M11: Yes | N11: No | O11: No | P11: No | Q11: Partially | R11: Partially | S11: Partially | T11: Yes
A12: Polyp Detection in Colonoscopy Videos via Boosted Multi-Scale Feature Fusion | B12: 2025 | C12: 10.1109/ISBI60581.2025.10981030 | D12: Yes | E12: Yes | G12: Yes | H12: Partially | I12: Yes | J12: No | K12: Yes | L12: Partially | M12: Yes | N12: No | O12: Partially | P12: No | Q12: Partially | R12: No | S12: No | T12: No
A13: Multimodal Learning for Enhanced Detection in Oral Cancer Screening | B13: 2025 | C13: 10.1109/ISBI60581.2025.10981235 | D13: Yes | E13: Yes | G13: Yes | H13: No | I13: No | J13: No | K13: Yes | L13: Partially | M13: Yes | N13: No | O13: No | P13: No | Q13: Partially | R13: Partially | S13: No | T13: No
A14: Accelerating Water Removal in MRSI Using Domain Knowledge-Based Deep Learning | B14: 2025 | C14: 10.1109/ISBI60581.2025.10980704 | D14: No
A15: BAY-MED: Bayesian Approximation for Post-Hoc Uncertainty in Medical Imaging | B15: 2025 | C15: 10.1109/ISBI60581.2025.10981251 | D15: No
A16: Conditional Generative Models for Contrast-Enhanced Synthesis of T1W and T1 Maps in Brain MRI | B16: 2025 | C16: 10.1109/ISBI60581.2025.10980893 | D16: No
A17: Gland Segmentation Using SAM with Cancer Grade As A Prompt | B17: 2025 | C17: 10.1109/ISBI60581.2025.10980744 | D17: No
A18: Instance-Aware Deep Learning for Liver Metastasis Segmentation | B18: 2025 | C18: 10.1109/ISBI60581.2025.10980698 | D18: No
A19: Video-Based Surgical Tool-Tip and Keypoint Tracking Using Multi-Frame Context-Driven Deep Learning Models | B19: 2025 | C19: 10.1109/ISBI60581.2025.10980959 | D19: No
A20: RadHop-Net: A Lightweight Radiomics-to-Error Regression for False Positive Reduction in MRI Prostate Cancer Detection | B20: 2025 | C20: 10.1109/ISBI60581.2025.10980816 | D20: Yes | E20: Yes | G20: Yes | H20: Partially | I20: Yes | J20: No | K20: Yes | L20: Yes | M20: Yes | N20: No | O20: Partially | P20: Partially | Q20: Partially | R20: Partially | S20: Partially | T20: No
A21: Segmentation of Hemorrhagic Stroke Using Graph Convolutional Network | B21: 2025 | C21: 10.1109/ISBI60581.2025.10980721 | D21: No
A22: Fully Unsupervised Deep Spectral Clustering for Retinal Vessel Segmentation | B22: 2025 | C22: 10.1109/ISBI60581.2025.10981224 | D22: No
A23: Diffusion-Based Multi-Degradation Remover for Fiber Bundle Image Restoration | B23: 2025 | C23: 10.1109/ISBI60581.2025.10980949 | D23: No
A24: BOrg: A Brain Organoid-Based Mitosis Dataset for Automatic Analysis of Brain Diseases | B24: 2025 | C24: 10.1109/ISBI60581.2025.10980679 | D24: No
A25: Deep Modeling and Optimization of Medical Image Classification | B25: 2025 | C25: 10.1109/ISBI60581.2025.10981184 | D25: Yes | E25: Yes | G25: Partially | H25: No | I25: No | J25: No | K25: Yes | L25: No | M25: Yes | N25: Yes | O25: Partially | P25: No | Q25: Partially | R25: Partially | S25: No | T25: Yes
A26: Prompting Medical Vision-Language Models to Mitigate Diagnosis Bias by Generating Realistic Dermoscopic Images | B26: 2025 | C26: 10.1109/ISBI60581.2025.10980892 | D26: No
A27: Classification of Oral Potentially Malignant Disorders Using Multimodal Feature Integration | B27: 2025 | C27: 10.1109/ISBI60581.2025.10980715 | D27: Yes | E27: Yes | G27: Yes | H27: Partially | I27: Yes | J27: No | K27: Yes | L27: Partially | M27: Yes | N27: Yes | O27: Partially | P27: No | Q27: Partially | R27: Partially | S27: Partially | T27: Yes
A28: C-ARM Guidance: A Self-Supervised Approach to Automated Positioning During Stroke Thrombectomy | B28: 2025 | C28: 10.1109/ISBI60581.2025.10980945 | D28: No
A29: Parameter Choices in Haarpsi for IQA with Medical Images | B29: 2025 | C29: 10.1109/ISBI60581.2025.10981227 | D29: No
A30: Measuring Impact of Super-Resolution on Spinal Cord MRI Scans: Lesion Detection Sensitivity, Variability, and Clinical Impact | B30: 2025 | C30: 10.1109/ISBI60581.2025.10981088 | D30: No
A31: Machine Learning Fairness for Depression Detection Using EEG Data | B31: 2025 | C31: 10.1109/ISBI60581.2025.10980986 | D31: No
A32: Spreading Depolarization Detection in Electrocorticogram Spectrogram Imaging by Deep Learning: Is it Just About Delta Band? | B32: 2025 | C32: 10.1109/ISBI60581.2025.10980689 | D32: Yes | E32: Yes | G32: Yes | H32: Partially | I32: Yes | J32: No | K32: Yes | L32: Partially | M32: Yes | N32: No | O32: Partially | P32: Partially | Q32: Partially | R32: Partially | S32: No | T32: No
A33: Attention-Driven Multi-Sequence Mri Feature Learning and Fusion for Breast Cancer Diagnosis | B33: 2025 | C33: 10.1109/ISBI60581.2025.10981203 | D33: Yes | E33: Yes | G33: Yes | H33: Partially | I33: Yes | J33: No | K33: Yes | L33: Partially | M33: Yes | N33: No | O33: Partially | P33: Partially | Q33: Partially | R33: Partially | S33: No | T33: No
A34: Beyond Occlusion: In Search for Near Real-Time Explainability of CNN-Based Prostate Cancer Classification | B34: 2025 | C34: 10.1109/ISBI60581.2025.10980802 | D34: No
A35: EMViR - Electron Microscopy Image Dataset Of Labelled Respiratory Viruses For Deep Learning Model Development | B35: 2025 | C35: 10.1109/ISBI60581.2025.10980686 | D35: No
A36: Generating Customized Prompts for Zero-Shot Rare Event Medical Image Classification Using LLM | B36: 2025 | C36: 10.1109/ISBI60581.2025.10981040 | D36: No
A37: Adaptive Whole-Body Pet Image Denoising Using 3D Diffusion Models with Controlnet | B37: 2025 | C37: 10.1109/ISBI60581.2025.10980878 | D37: No
A38: Easy and Hard Partitions: An Investigation On Dataset Partitions in Biomedical Image Analysis | B38: 2025 | C38: 10.1109/ISBI60581.2025.10981289 | D38: No
A39: Enhancing Dementia Detection: Augmenting the Face Mesh | B39: 2025 | C39: 10.1109/ISBI60581.2025.10980957 | D39: Yes | E39: Yes | G39: Yes | H39: Partially | I39: Yes | J39: No | K39: Yes | L39: No | M39: Yes | N39: No | O39: Partially | P39: No | Q39: Partially | R39: Partially | S39: No | T39: No
A40: Medical Image Quality Assessment Based on Probability of Necessity and Sufficiency | B40: 2025 | C40: 10.1109/ISBI60581.2025.10981239 | D40: No
A41: Large-Scale Radiomics Analysis for Prostate Cancer Detection Harnessing Machine and Deep Learning Models | B41: 2025 | C41: 10.1109/ISBI60581.2025.10980708 | D41: Yes | E41: Yes | G41: Yes | H41: Partially | I41: Yes | J41: No | K41: Yes | L41: Yes | M41: Yes | N41: Yes | O41: Yes | P41: Partially | Q41: Partially | R41: Partially | S41: Partially | T41: No
A42: Robust Training of Deep Learning Models for Mammogram Classification | B42: 2025 | C42: 10.1109/ISBI60581.2025.10980787 | D42: Yes | E42: Yes | G42: Partially | H42: No | I42: Yes | J42: No | K42: Yes | L42: Yes | M42: Yes | N42: No | O42: Partially | P42: No | Q42: Partially | R42: Partially | S42: No | T42: No
A43: Ultrasound Nerve Segmentation with Deep Learning for Leprosy | B43: 2025 | C43: 10.1109/ISBI60581.2025.10980980 | D43: No
A44: Beyond the Last Scan: The Role of Longitudinal Neuroimaging in Predicting Conversion to Alzheimer's Disease at Different Stages | B44: 2025 | C44: 10.1109/ISBI60581.2025.10981022 | D44: No
A45: Semantic Reconstruction from Fnirs Using Recurrent Neural Networks | B45: 2025 | C45: 10.1109/ISBI60581.2025.10981123 | D45: No
A46: Towards Multi-Label Open Set Diagnosis for Medical Images | B46: 2025 | C46: 10.1109/ISBI60581.2025.10980926 | D46: No
A47: Adaptive Collaborative Learning Polyp Segmentation Framework Based on Contour-Driven Parallel Attention Network | B47: 2025 | C47: 10.1109/ISBI60581.2025.10981193 | D47: No
A48: Segmentation of Cardiovascular Structures from Screening Non-contrast CT Calcium Score Images Using the Tuned CardioNC-Segmentator on Virtual CTA Images | B48: 2025 | C48: 10.1109/ISBI60581.2025.10981214 | D48: No
A49: Connectome-GTC: A Unified Framework for Brain Functional and Structural Connectomes Generation, Translation, and Classification | B49: 2025 | C49: 10.1109/ISBI60581.2025.10981216 | D49: No
A50: Masked Momentum Contrastive Dynamic Transformer for Self-Supervised Functional Connectivity Representation Learning | B50: 2025 | C50: 10.1109/ISBI60581.2025.10980976 | D50: No
A51: A Comparison of Object Detection and Phrase Grounding Models in Chest X-Ray Abnormality Localization Using Eye-Tracking Data | B51: 2025 | C51: 10.1109/ISBI60581.2025.10981290 | D51: No
A52: ASDC-NET: Anterior Segment Disease Classification Network Based on Slit-Lamp Images | B52: 2025 | C52: 10.1109/ISBI60581.2025.10980943 | D52: No
A53: Active Prompt Tuning Enables GPT-4O to do Efficient Classification of Microscopy Images | B53: 2025 | C53: 10.1109/ISBI60581.2025.10981114 | D53: No
A54: Enhancing Lung Segmentation Algorithms to Ensure Inclusion of Juxtapleural Nodules | B54: 2025 | C54: 10.1109/ISBI60581.2025.10981085 | D54: No
A55: T2-Only Prostate Cancer Prediction by Meta-Learning from BI-Parametric MR Imaging | B55: 2025 | C55: 10.1109/ISBI60581.2025.10981221 | D55: Yes | E55: Yes | G55: Yes | H55: Partially | I55: Yes | J55: Yes | K55: Yes | L55: Yes | M55: Yes | N55: Yes | O55: Partially | P55: No | Q55: Partially | R55: Partially | S55: Yes | T55: Yes
A56: Classifying Coronary Artery Calcification Risk using Radiomics from Non-Gated CT Scans | B56: 2025 | C56: 10.1109/ISBI60581.2025.10980918 | D56: Yes | E56: Yes | G56: Yes | H56: No | I56: Yes | J56: No | K56: Yes | L56: No | M56: Yes | N56: No | O56: No | P56: No | Q56: No | R56: No | S56: No | T56: No
A57: Explainsegnet: Interpretable Segmentation for Alzheimer's Diagnosis | B57: 2025 | C57: 10.1109/ISBI60581.2025.10981081 | D57: No
A58: Identifying Brain Strokes by Image Analysis Using Transfer Learning | B58: 2025 | C58: 10.1109/ISBI60581.2025.10981247 | D58: Yes | E58: Yes | G58: Yes | H58: Partially | I58: Yes | J58: Yes | K58: Yes | L58: No | M58: Yes | N58: No | O58: Partially | P58: No | Q58: Partially | R58: Partially | S58: No | T58: No
A59: Advancing OCT-Based Retinal Disease Classification with XLSTM: A Framework for Variable-Length Volume Processing | B59: 2025 | C59: 10.1109/ISBI60581.2025.10981206 | D59: Yes | E59: Yes | G59: Yes | H59: Partially | I59: Yes | J59: No | K59: Yes | L59: Partially | M59: Yes | N59: Yes | O59: Yes | P59: No | Q59: Partially | R59: Partially | S59: No | T59: No
A60: CINEPRO: Robust Training of Foundation Models for Cancer Detection in Prostate Ultrasound Cineloops | B60: 2025 | C60: 10.1109/ISBI60581.2025.10981222 | D60: Yes | E60: Yes | G60: Yes | H60: Partially | I60: Yes | J60: No | K60: Yes | L60: Partially | M60: Yes | N60: No | O60: Partially | P60: Partially | Q60: Partially | R60: Partially | S60: Partially | T60: Yes
A61: Semi-Supervised Multimodal Multi-Instance Learning for Aortic Stenosis Diagnosis | B61: 2025 | C61: 10.1109/ISBI60581.2025.10981205 | D61: Yes | E61: Yes | G61: Yes | H61: Partially | I61: Yes | J61: No | K61: Yes | L61: Partially | M61: Yes | N61: Yes | O61: Partially | P61: No | Q61: Partially | R61: Yes | S61: No | T61: No
A62: Causal Modeling of FMRI Time-Series for Interpretable Autism Spectrum Disorder Classification | B62: 2025 | C62: 10.1109/ISBI60581.2025.10980933 | D62: Yes | E62: Yes | G62: Yes | H62: Partially | I62: Yes | J62: No | K62: Yes | L62: Partially | M62: Yes | N62: No | O62: Partially | P62: No | Q62: Partially | R62: Partially | S62: No | T62: No
A63: Towards Improved Cervical Cancer Screening: Vision Transformer-Based Classification and Interpretability | B63: 2025 | C63: 10.1109/ISBI60581.2025.10981006 | D63: Yes | E63: Yes | G63: Yes | H63: Partially | I63: Yes | J63: No | K63: Yes | L63: No | M63: Yes | N63: No | O63: No | P63: No | Q63: Partially | R63: Partially | S63: No | T63: Yes
A64: ISGM-DR: Important Slice-Guided Model for Diabetic Retinopathy Diagnosis Using 3D Oct Images | B64: 2025 | C64: 10.1109/ISBI60581.2025.10980677 | D64: Yes | E64: Yes | G64: Yes | H64: Partially | I64: Yes | J64: No | K64: Yes | L64: No | M64: Yes | N64: No | O64: No | P64: No | Q64: Partially | R64: Partially | S64: No | T64: No
A65: Automated Detection of Mitotic Figures in Glioma Tissues Using Deep Learning | B65: 2025 | C65: 10.1109/ISBI60581.2025.10981196 | D65: Yes | E65: Yes | G65: Yes | H65: Partially | I65: Yes | J65: No | K65: Partially | L65: No | M65: Yes | N65: Yes | O65: Partially | P65: No | Q65: Partially | R65: Partially | S65: No | T65: Yes
A66: White Light Specular Reflection Data Augmentation for Deep Learning Polyp Detection | B66: 2025 | C66: 10.1109/ISBI60581.2025.10981109 | D66: Yes | E66: Yes | G66: Yes | H66: Partially | I66: Yes | J66: No | K66: Yes | L66: No | M66: Yes | N66: No | O66: Partially | P66: No | Q66: Partially | R66: No | S66: No | T66: No
A67: Scalable Whole Slide Image Representation Using K-Means Clustering and Fisher Vector Aggregation | B67: 2025 | C67: 10.1109/ISBI60581.2025.10981271 | D67: No
A68: Towards Better Interpretability of Sepsis Prediction by Deep Neural Networks with Variable-Wise Attribution Maps | B68: 2025 | C68: 10.1109/ISBI60581.2025.10980887 | D68: No
A69: Multi-Phase Attention for Early Stage Hepatocellular Carcinoma Segmentation from Contrast Enhanced Liver MRI | B69: 2025 | C69: 10.1109/ISBI60581.2025.10980806 | D69: No
A70: Exploring the Use of Generative Adversarial Networks for Automated Dental Preparation Design | B70: 2025 | C70: 10.1109/ISBI60581.2025.10980970 | D70: No
A71: A Hierarchical Slice Attention Network for Appendicitis Classification in 3D CT Scans | B71: 2025 | C71: 10.1109/ISBI60581.2025.10981299 | D71: Yes | E71: Yes | G71: Yes | H71: Partially | I71: Yes | J71: No | K71: Yes | L71: No | M71: Yes | N71: Yes | O71: Yes | P71: No | Q71: Partially | R71: Partially | S71: No | T71: No
A72: Guiding the Classification of Hepatocellular Carcinoma on 3D CT-Scans Using Deep and Handcrafted Radiological Features | B72: 2025 | C72: 10.1109/ISBI60581.2025.10981163 | D72: Yes | E72: Yes | G72: Yes | H72: Partially | I72: Yes | J72: No | K72: Yes | L72: Yes | M72: Yes | N72: Yes | O72: Partially | P72: No | Q72: Partially | R72: Partially | S72: No | T72: No
A73: Can Score-Based Generative Modeling Effectively Handle Medical Image Classification? | B73: 2025 | C73: 10.1109/ISBI60581.2025.10980700 | D73: No
A74: SRE-CONV: Symmetric Rotation Equivariant Convolution for Biomedical Image Classification | B74: 2025 | C74: 10.1109/ISBI60581.2025.10981270 | D74: No
A75: Efficient Human-in-the-Loop Pancreatic Tumor Annotation via Large-Scale Pre-Trained Model with Adaptive Post-Processing | B75: 2025 | C75: 10.1109/ISBI60581.2025.10981189 | D75: No
A76: Evaluating Data Augmentation Strategies for Robust Cross-Dataset Generalization in Wound Classification | B76: 2025 | C76: 10.1109/ISBI60581.2025.10980725 | D76: No
A77: Mitral Valve Deep Learning Localization in CT Scans for MIMVR Surgery | B77: 2025 | C77: 10.1109/ISBI60581.2025.10980942 | D77: No
A78: FMUNet: Frequency Modulation-Based UNet for Octa Segmentation | B78: 2025 | C78: 10.1109/ISBI60581.2025.10980982 | D78: No
A79: Hybrid DL Classification Model Based on CNN and Transformer for Pap Smear Cells | B79: 2025 | C79: 10.1109/ISBI60581.2025.10981236 | D79: Yes | E79: Yes | G79: Yes | H79: Partially | I79: Yes | J79: N.A | K79: Yes | L79: No | M79: Yes | N79: Yes | O79: Partially | P79: No | Q79: Partially | R79: Partially | S79: Partially | T79: Yes
A80: Needles in the Haystack-Rapid Error Detection for Cell Tracking Solutions | B80: 2025 | C80: 10.1109/ISBI60581.2025.10980906 | D80: No
A81: Z-Stack Scanning can Improve AI Detection of Mitosis: A Case Study of Meningiomas | B81: 2025 | C81: 10.1109/ISBI60581.2025.10980734 | D81: No
A82: Enhanced Cervical Vertebral Maturation Assessment Using AI-Based Imaging Analysis System | B82: 2025 | C82: 10.1109/ISBI60581.2025.10981050 | D82: Yes | E82: Yes | G82: Yes | H82: Partially | I82: Yes | J82: No | K82: Yes | L82: Partially | M82: Yes | N82: No | O82: Partially | P82: No | Q82: Partially | R82: Partially | S82: Partially | T82: No
A83: Improving Quality Control of MRI Images Using Synthetic Motion Data | B83: 2025 | C83: 10.1109/ISBI60581.2025.10981056 | D83: No
A84: Cell Image Classification with Polygon-Guided Extraction for Glioma Mitosis Detection | B84: 2025 | C84: 10.1109/ISBI60581.2025.10980953 | D84: Yes | E84: No | F84: Segmentation
A85: Optimizing Residual Networks for Cervical Cancer Screening: A Study on the Pap Smear Cell Classification Challenge | B85: 2025 | C85: 10.1109/ISBI60581.2025.10980705 | D85: Yes | E85: Yes | G85: Yes | H85: Partially | I85: Yes | J85: No | K85: Yes | L85: Partially | M85: Yes | N85: No | O85: Partially | P85: No | Q85: Partially | R85: Partially | S85: Partially | T85: No
A86: Enhanced Mitotic Figure Detection in Glioma Using Super-Resolution Images and High-Frequency Content Maps | B86: 2025 | C86: 10.1109/ISBI60581.2025.10980984 | D86: Yes | E86: Yes | G86: Yes | H86: Partially | I86: Yes | J86: No | K86: Yes | L86: Yes | M86: Yes | N86: No | O86: Partially | P86: Partially | Q86: Partially | R86: Partially | S86: No | T86: No
A87: Combining 4D Hyperspectral Imaging With CNN for Nerve and Ligament Differentiation | B87: 2025 | C87: 10.1109/ISBI60581.2025.10981284 | D87: No
A88: DASAM: Medical Domain Adaptation of Segment Anything Model Without Further Pre-Training | B88: 2025 | C88: 10.1109/ISBI60581.2025.10980758 | D88: No
A89: Class Fusion of Support Vector Machines with Deep Learning Features for Oral Cancer Histopathology Classification | B89: 2025 | C89: 10.1109/ISBI60581.2025.10980934 | D89: Yes | E89: Yes | G89: Yes | H89: Partially | I89: Yes | J89: No | K89: Yes | L89: No | M89: Yes | N89: No | O89: Partially | P89: No | Q89: Partially | R89: Partially | S89: Partially | T89: No
A90: An Attention Based Model for Histopathology Image Nuclei Segmentation | B90: 2025 | C90: 10.1109/ISBI60581.2025.10981150 | D90: No
A91: Unsupervised Normative Learning for Quality Assessment on Diffusion MRI | B91: 2025 | C91: 10.1109/ISBI60581.2025.10981188 | D91: No
A92: Joint Reconstruction of Dynamic PET Activity and Kinetic Parametric Images Using Learnable Descent Framework | B92: 2025 | C92: 10.1109/ISBI60581.2025.10980818 | D92: No
A93: CLISC: Bridging Clip and SAM by Enhanced CAM for Unsupervised Brain Tumor Segmentation | B93: 2025 | C93: 10.1109/ISBI60581.2025.10980784 | D93: No
A94: AI-Based Thermal Video Analysis in Privacy-Preserving Healthcare: A Case Study on Detecting Time of Birth | B94: 2025 | C94: 10.1109/ISBI60581.2025.10980757 | D94: No
A95: Melanoma Detection with Uncertainty Quantification | B95: 2025 | C95: 10.1109/ISBI60581.2025.10981143 | D95: Yes | E95: Yes | G95: Yes | H95: Partially | I95: Partially | J95: Partially | K95: Yes | L95: Partially | M95: Yes | N95: Yes | O95: No | P95: No | Q95: Partially | R95: Partially | S95: Yes | T95: Yes
A96: Deep Learning-Driven Automated Aortic Valve Calcification Assessment in CT Calcium Score Screening Images | B96: 2025 | C96: 10.1109/ISBI60581.2025.10980963 | D96: Yes | E96: Yes | G96: Yes | H96: Partially | I96: Yes | J96: N.A | K96: Yes | L96: Partially | M96: Yes | N96: Yes | O96: Partially | P96: No | Q96: Partially | R96: Partially | S96: Partially | T96: No
A97: IHA-YOLO: Inter-Head Attention for Real-Time Cell Detection | B97: 2025 | C97: 10.1109/ISBI60581.2025.10981067 | D97: Yes | E97: Yes | G97: Yes | H97: Partially | I97: Yes | J97: No | K97: Yes | L97: No | M97: Yes | N97: No | O97: Partially | P97: No | Q97: Partially | R97: Partially | S97: No | T97: Yes
A98: LF-MAMBA: A State Space Model-Based Framework for Accurate Bilateral Hippocampi Segmentation in Low-Field Pediatric MRI | B98: 2025 | C98: 10.1109/ISBI60581.2025.10980888 | D98: No
A99: Enhanced Graph Representation for Reliable Retinal Vessel Analysis: CLSA Population-Based Study | B99: 2025 | C99: 10.1109/ISBI60581.2025.10981176 | D99: No
A100: Hierarchical Log Bayesian Neural Network for Enhanced Aorta Segmentation | B100: 2025 | C100: 10.1109/ISBI60581.2025.10980947 | D100: No
...

Sheet Hoja1
C70: Data sources (CLAIM 7) | D70: Inclusion and exclusion criteria (CLAIM 8) | E70: Selection of data subsets (CLAIM 10) | F70: How missing data were handled (CLAIM 12) | G70: Metrics of model performance (CLAIM 28) | H70: Statistical measures of significance and uncertainty (CLAIM 29) | I70: Evaluation on internal data (CLAIM 32) | J70: Testing on external data (CLAIM 33) | K70: Numbers of patients or examinations included and excluded (CLAIM 35) | L70: Demographic and clinical characteristics of cases in each partition (CLAIM36) | M70: Performance metrics and measures of statistical uncertainty (CLAIM 37) | N70: Estimates of diagnostic performance and their precision (CLIAM 38) | O70: Failure analysis of incorrect results (CLAIM 39) | P70: Public availability (code)
B71: Yes | C71: =(COUNTIF(search_ISBI!G2:G686,"Yes")/COUNTA(search_ISBI!G2:G686)) -> 0.92592593 | D71: 10 | E71: =(COUNTIF(search_ISBI!I2:I686,"Yes")/COUNTA(search_ISBI!I2:I686)) -> 0.86419753 | F71: =(COUNTIF(search_ISBI!J2:J686,"Yes")/COUNTA(search_ISBI!J2:J686)) -> 0.082304527 | G71: =(COUNTIF(search_ISBI!K2:K686,"Yes")/COUNTA(search_ISBI!K2:K686)) -> 0.87654321 | H71: =(COUNTIF(search_ISBI!L2:L686,"Yes")/COUNTA(search_ISBI!L2:L686)) -> 0.19341564 | I71: =(COUNTIF(search_ISBI!M2:M686,"Yes")/COUNTA(search_ISBI!M2:M686)) -> 0.97942387 | J71: =(COUNTIF(search_ISBI!N2:N686,"Yes")/COUNTA(search_ISBI!N2:N686)) -> 0.16049383 | K71: =(COUNTIF(search_ISBI!O2:O686,"Yes")/COUNTA(search_ISBI!O2:O686)) -> 0.061728395 | L71: =(COUNTIF(search_ISBI!P2:P686,"Yes")/COUNTA(search_ISBI!P2:P686)) -> 0.049382716 | ... P71: =(COUNTIF(search_ISBI!T2:T686,"Yes")/COUNTA(search_ISBI!T2:T686)) -> 0.18930041
B72: No | C72: =COUNTIF(search_ISBI!G2:G686,"No")/COUNTA(search_ISBI!G2:G686) -> 0 | D72: =COUNTIF(search_ISBI!H2:H686,"No")/COUNTA(search_ISBI!H2:H686) -> 0.10699588 | E72: =COUNTIF(search_ISBI!I2:I686,"No")/COUNTA(search_ISBI!I2:I686) -> 0.037037037 | F72: =COUNTIF(search_ISBI!J2:J686,"No")/COUNTA(search_ISBI!J2:J686) -> 0.83127572 | G72: =COUNTIF(search_ISBI!K2:K686,"No")/COUNTA(search_ISBI!K2:K686) -> 0.0041152263 | H72: =COUNTIF(search_ISBI!L2:L686,"No")/COUNTA(search_ISBI!L2:L686) -> 0.37037037 | I72: =COUNTIF(search_ISBI!M2:M686,"No")/COUNTA(search_ISBI!M2:M686) -> 0.020576132 | J72: =COUNTIF(search_ISBI!N2:N686,"No")/COUNTA(search_ISBI!N2:N686) -> 0.82304527 | ... P72: =COUNTIF(search_ISBI!T2:T686,"No")/COUNTA(search_ISBI!T2:T686) -> 0.81069959
B73: Partially | C73: =COUNTIF(search_ISBI!G2:G686,"Partially")/COUNTA(search_ISBI!G2:G686) -> 0.074074074 | D73: =COUNTIF(search_ISBI!H2:H686,"Partially")/COUNTA(search_ISBI!H2:H686) -> 0.81069959 | E73: =COUNTIF(search_ISBI!I2:I686,"Partially")/COUNTA(search_ISBI!I2:I686) -> 0.094650206 | F73: =COUNTIF(search_ISBI!J2:J686,"Partially")/COUNTA(search_ISBI!J2:J686) -> 0.049382716 | G73: =COUNTIF(search_ISBI!K2:K686,"Partially")/COUNTA(search_ISBI!K2:K686) -> 0.11934156 | H73: =COUNTIF(search_ISBI!L2:L686,"Partially")/COUNTA(search_ISBI!L2:L686) -> 0.43621399 | I73: =COUNTIF(search_ISBI!M2:M686,"Partially")/COUNTA(search_ISBI!M2:M686) -> 0 | J73: =COUNTIF(search_ISBI!N2:N686,"Partially")/COUNTA(search_ISBI!N2:N686) -> 0.016460905 | ... P73: =COUNTIF(search_ISBI!T2:T686,"Partially")/COUNTA(search_ISBI!T2:T686) -> 0
B74: N.A | C74: =COUNTIF(search_ISBI!G2:G686,"N.A")/COUNTA(search_ISBI!G2:G686) -> 0 | D74: =COUNTIF(search_ISBI!H2:H686,"N.A")/COUNTA(search_ISBI!H2:H686) -> 0 | E74: =COUNTIF(search_ISBI!I2:I686,"N.A")/COUNTA(search_ISBI!I2:I686) -> 0.0041152263 | F74: =COUNTIF(search_ISBI!J2:J686,"N.A")/COUNTA(search_ISBI!J2:J686) -> 0.037037037 | G74: =COUNTIF(search_ISBI!K2:K686,"N.A")/COUNTA(search_ISBI!K2:K686) -> 0 | H74: =COUNTIF(search_ISBI!L2:L686,"N.A")/COUNTA(search_ISBI!L2:L686) -> 0 | I74: =COUNTIF(search_ISBI!M2:M686,"N.A")/COUNTA(search_ISBI!M2:M686) -> 0 | J74: =COUNTIF(search_ISBI!N2:N686,"N.A")/COUNTA(search_ISBI!N2:N686) -> 0 | ... P74: =COUNTIF(search_ISBI!T2:T686,"N.A")/COUNTA(search_ISBI!T2:T686) -> 0
